inmanta_plugins/kubernetes/__init__.py
inmanta_plugins/kubernetes/setup.cfg
inmanta_plugins/kubernetes/files/.gitkeep
inmanta_plugins/kubernetes/model/_init.cf
inmanta_plugins/kubernetes/model/infra/_init.cf
inmanta_plugins/kubernetes/model/resources/_init.cf
inmanta_plugins/kubernetes/resources/__init__.py
inmanta_plugins/kubernetes/resources/cluster_resource.py
inmanta_plugins/kubernetes/resources/cluster_role_binding_resource.py
inmanta_plugins/kubernetes/resources/cluster_role_resource.py
inmanta_plugins/kubernetes/resources/config_map_resource.py
inmanta_plugins/kubernetes/resources/deployment_resource.py
inmanta_plugins/kubernetes/resources/namespace_resource.py
inmanta_plugins/kubernetes/resources/namespaced_resource.py
inmanta_plugins/kubernetes/resources/pod_resource.py
inmanta_plugins/kubernetes/resources/role_binding_resource.py
inmanta_plugins/kubernetes/resources/role_resource.py
inmanta_plugins/kubernetes/resources/secret_resource.py
inmanta_plugins/kubernetes/resources/service_account_resource.py
inmanta_plugins/kubernetes/resources/service_resource.py
inmanta_plugins/kubernetes/resources/stateful_set_resource.py
inmanta_plugins/kubernetes/templates/.gitkeep
inmanta_module_kubernetes-0.0.4.dist-info/METADATA
inmanta_module_kubernetes-0.0.4.dist-info/WHEEL
inmanta_module_kubernetes-0.0.4.dist-info/top_level.txt
inmanta_module_kubernetes-0.0.4.dist-info/RECORD
